pysonio/__init__.py
pysonio/attendance.py
pysonio/browser.py
pysonio-0.0.5.dist-info/METADATA
pysonio-0.0.5.dist-info/RECORD
pysonio-0.0.5.dist-info/WHEEL
pysonio-0.0.5.dist-info/top_level.txt
